[{
    "ms_v": 3.83,
    "temp_s_5": 26.0,
    "wnd_max_30": 18.47,
    "std_dev": 8.62,
    "wnd_prom_0": 8.84,
    "temp_s_0": 34.2,
    "status": "ok",
    "rep": "1",
    "wnd_max_200": 27.11,
    "median": 20.0,
    "sec_noise": 16.0,
    "volume": 3.59,
    "temp_l_10": 22.3,
    "orientation": "H",
    "wnd_min_0": 6.42,
    "ms_h": 91.87,
    "filename": "19_2_21_B1H1.txt",
    "temp_l_5": 25.6,
    "wnd_min_30": 6.94,
    "block": "1",
    "entropy": 6.31,
    "wnd_prom_200": 18.79,
    "density": 26.67,
    "temp_s_10": 22.2,
    "wnd_max_0": 11.25,
    "wnd_prom_30": 12.71,
    "max_height": 90,
    "treatment": "H",
    "temp_l_0": 32.3,
    "date": "21/2/19",
    "wnd_min_200": 10.46
}, {
    "ms_v": 1.54,
    "temp_s_5": 26.7,
    "wnd_max_30": 18.47,
    "std_dev": 7.45,
    "wnd_prom_0": 8.84,
    "temp_s_0": 38.8,
    "status": "ok",
    "rep": "2",
    "wnd_max_200": 27.11,
    "median": 9.0,
    "sec_noise": 20.0,
    "volume": 1.77,
    "temp_l_10": 22.3,
    "orientation": "H",
    "wnd_min_0": 6.42,
    "ms_h": 59.1,
    "filename": "19_2_21_B1H2.txt",
    "temp_l_5": 26.2,
    "wnd_min_30": 6.94,
    "block": "1",
    "entropy": 5.35,
    "wnd_prom_200": 18.79,
    "density": 34.26,
    "temp_s_10": 22.5,
    "wnd_max_0": 11.25,
    "wnd_prom_30": 12.71,
    "max_height": 108,
    "treatment": "H",
    "temp_l_0": 36.4,
    "date": "21/2/19",
    "wnd_min_200": 10.46
}, {
    "ms_v": 0.0,
    "temp_s_5": 25.6,
    "wnd_max_30": 18.47,
    "std_dev": 6.25,
    "wnd_prom_0": 8.84,
    "temp_s_0": 33.2,
    "status": "ok",
    "rep": "3",
    "wnd_max_200": 27.11,
    "median": 15.0,
    "sec_noise": 39.0,
    "volume": 2.57,
    "temp_l_10": 22.8,
    "orientation": "H",
    "wnd_min_0": 6.42,
    "ms_h": 184.13,
    "filename": "19_2_21_B1H3.txt",
    "temp_l_5": 26.1,
    "wnd_min_30": 6.94,
    "block": "1",
    "entropy": 7.7,
    "wnd_prom_200": 18.79,
    "density": 71.59,
    "temp_s_10": 23.1,
    "wnd_max_0": 11.25,
    "wnd_prom_30": 12.71,
    "max_height": 29,
    "treatment": "H",
    "temp_l_0": 32.2,
    "date": "21/2/19",
    "wnd_min_200": 10.46
}, {
    "ms_v": 14.0,
    "temp_s_5": 29.0,
    "wnd_max_30": 18.71,
    "std_dev": 5.97,
    "wnd_prom_0": 7.05,
    "temp_s_0": 38.7,
    "status": "ok",
    "rep": "1",
    "wnd_max_200": 26.05,
    "median": 16.0,
    "sec_noise": 19.0,
    "volume": 2.85,
    "temp_l_10": 22.3,
    "orientation": "H",
    "wnd_min_0": 5.78,
    "ms_h": 90.03,
    "filename": "19_2_21_B1P1.txt",
    "temp_l_5": 26.0,
    "wnd_min_30": 8.77,
    "block": "1",
    "entropy": 6.88,
    "wnd_prom_200": 20.39,
    "density": 36.45,
    "temp_s_10": 23.1,
    "wnd_max_0": 8.32,
    "wnd_prom_30": 13.74,
    "max_height": 46,
    "treatment": "P",
    "temp_l_0": 35.8,
    "date": "21/2/19",
    "wnd_min_200": 14.74
}, {
    "ms_v": 15.49,
    "temp_s_5": 27.8,
    "wnd_max_30": 18.71,
    "std_dev": 7.12,
    "wnd_prom_0": 7.05,
    "temp_s_0": 38.3,
    "status": "ok",
    "rep": "2",
    "wnd_max_200": 26.05,
    "median": 17,
    "sec_noise": 11.0,
    "volume": 3.06,
    "temp_l_10": 23.3,
    "orientation": "H",
    "wnd_min_0": 5.78,
    "ms_h": 80.7,
    "filename": "19_2_21_B1P2.txt",
    "temp_l_5": 28.2,
    "wnd_min_30": 8.77,
    "block": "1",
    "entropy": 6.72,
    "wnd_prom_200": 20.39,
    "density": 31.45,
    "temp_s_10": 23.2,
    "wnd_max_0": 8.32,
    "wnd_prom_30": 13.74,
    "max_height": 59,
    "treatment": "P",
    "temp_l_0": 36.6,
    "date": "21/2/19",
    "wnd_min_200": 14.74
}, {
    "ms_v": 25.68,
    "temp_s_5": 28.8,
    "wnd_max_30": 18.71,
    "std_dev": 8.27,
    "wnd_prom_0": 7.05,
    "temp_s_0": 43.6,
    "status": "ok",
    "rep": "3",
    "wnd_max_200": 26.05,
    "median": 16.0,
    "sec_noise": 15.0,
    "volume": 2.86,
    "temp_l_10": 23.0,
    "orientation": "H",
    "wnd_min_0": 5.78,
    "ms_h": 124.35,
    "filename": "19_2_21_B1P3.txt",
    "temp_l_5": 26.2,
    "wnd_min_30": 8.77,
    "block": "1",
    "entropy": 7.63,
    "wnd_prom_200": 20.39,
    "density": 52.45,
    "temp_s_10": 23.5,
    "wnd_max_0": 8.32,
    "wnd_prom_30": 13.74,
    "max_height": 40,
    "treatment": "P",
    "temp_l_0": 35.1,
    "date": "21/2/19",
    "wnd_min_200": 14.74
}, {
    "ms_v": 49.54,
    "temp_s_5": 27.7,
    "wnd_max_30": 9.67,
    "std_dev": 61.71,
    "wnd_prom_0": 5.34,
    "temp_s_0": 36.9,
    "status": "ok",
    "rep": "1",
    "wnd_max_200": 27.71,
    "median": 51.0,
    "sec_noise": 7.0,
    "volume": 12.7,
    "temp_l_10": 23.1,
    "orientation": "H",
    "wnd_min_0": 4.37,
    "ms_h": 37.85,
    "filename": "19_2_21_B1V1.txt",
    "temp_l_5": 28.2,
    "wnd_min_30": 7.2,
    "block": "1",
    "entropy": 6.54,
    "wnd_prom_200": 20.15,
    "density": 6.88,
    "temp_s_10": 23.2,
    "wnd_max_0": 6.3,
    "wnd_prom_30": 8.44,
    "max_height": 487,
    "treatment": "V",
    "temp_l_0": 34.9,
    "date": "21/2/19",
    "wnd_min_200": 12.59
}, {
    "ms_v": 41.89,
    "temp_s_5": 28.3,
    "wnd_max_30": 9.67,
    "std_dev": 37.88,
    "wnd_prom_0": 5.34,
    "temp_s_0": 36.1,
    "status": "ok",
    "rep": "2",
    "wnd_max_200": 27.71,
    "median": 40.0,
    "sec_noise": 9.0,
    "volume": 8.86,
    "temp_l_10": 23.3,
    "orientation": "H",
    "wnd_min_0": 4.37,
    "ms_h": 28.56,
    "filename": "19_2_21_B1V2.txt",
    "temp_l_5": 27.2,
    "wnd_min_30": 7.2,
    "block": "1",
    "entropy": 7.57,
    "wnd_prom_200": 20.15,
    "density": 7.95,
    "temp_s_10": 23.3,
    "wnd_max_0": 6.3,
    "wnd_prom_30": 8.44,
    "max_height": 159,
    "treatment": "V",
    "temp_l_0": 37.0,
    "date": "21/2/19",
    "wnd_min_200": 12.59
}, {
    "ms_v": 52.09,
    "temp_s_5": 29.6,
    "wnd_max_30": 9.67,
    "std_dev": 43.85,
    "wnd_prom_0": 5.34,
    "temp_s_0": 43.4,
    "status": "ok",
    "rep": "3",
    "wnd_max_200": 27.71,
    "median": 64.0,
    "sec_noise": 8.0,
    "volume": 12.83,
    "temp_l_10": 23.5,
    "orientation": "H",
    "wnd_min_0": 4.37,
    "ms_h": 30.45,
    "filename": "19_2_21_B1V3.txt",
    "temp_l_5": 28.9,
    "wnd_min_30": 7.2,
    "block": "1",
    "entropy": 6.98,
    "wnd_prom_200": 20.15,
    "density": 6.43,
    "temp_s_10": 23.2,
    "wnd_max_0": 6.3,
    "wnd_prom_30": 8.44,
    "max_height": 322,
    "treatment": "V",
    "temp_l_0": 41.4,
    "date": "21/2/19",
    "wnd_min_200": 12.59
}, {
    "ms_v": 2.56,
    "temp_s_5": 26.7,
    "wnd_max_30": 11.92,
    "std_dev": 5.89,
    "wnd_prom_0": 8.26,
    "temp_s_0": 36.9,
    "status": "ok",
    "rep": "1",
    "wnd_max_200": 25.84,
    "median": 13.0,
    "sec_noise": 13.0,
    "volume": 2.24,
    "temp_l_10": 22.9,
    "orientation": "H",
    "wnd_min_0": 6.17,
    "ms_h": 78.49,
    "filename": "19_2_21_B2H1.txt",
    "temp_l_5": 26.7,
    "wnd_min_30": 7.42,
    "block": "2",
    "entropy": 6.86,
    "wnd_prom_200": 21.58,
    "density": 36.25,
    "temp_s_10": 22.8,
    "wnd_max_0": 10.35,
    "wnd_prom_30": 9.67,
    "max_height": 47,
    "treatment": "H",
    "temp_l_0": 37.0,
    "date": "21/2/19",
    "wnd_min_200": 17.32
}, {
    "ms_v": 3.08,
    "temp_s_5": 30.7,
    "wnd_max_30": 11.92,
    "std_dev": 8.03,
    "wnd_prom_0": 8.26,
    "temp_s_0": 34.1,
    "status": "ok",
    "rep": "2",
    "wnd_max_200": 25.84,
    "median": 15.0,
    "sec_noise": 16.0,
    "volume": 2.8,
    "temp_l_10": 24.1,
    "orientation": "H",
    "wnd_min_0": 6.17,
    "ms_h": 93.08,
    "filename": "19_2_21_B2H2.txt",
    "temp_l_5": 28.8,
    "wnd_min_30": 7.42,
    "block": "2",
    "entropy": 6.24,
    "wnd_prom_200": 21.58,
    "density": 34.29,
    "temp_s_10": 24.5,
    "wnd_max_0": 10.35,
    "wnd_prom_30": 9.67,
    "max_height": 85,
    "treatment": "H",
    "temp_l_0": 32.9,
    "date": "21/2/19",
    "wnd_min_200": 17.32
}, {
    "ms_v": 1.81,
    "temp_s_5": 30.6,
    "wnd_max_30": 11.92,
    "std_dev": 7.09,
    "wnd_prom_0": 8.26,
    "temp_s_0": 28.8,
    "status": "ok",
    "rep": "3",
    "wnd_max_200": 25.84,
    "median": 16.0,
    "sec_noise": 19.0,
    "volume": 2.74,
    "temp_l_10": 23.7,
    "orientation": "H",
    "wnd_min_0": 6.17,
    "ms_h": 83.54,
    "filename": "19_2_21_B2H3.txt",
    "temp_l_5": 30.6,
    "wnd_min_30": 7.42,
    "block": "2",
    "entropy": 7.64,
    "wnd_prom_200": 21.58,
    "density": 31.15,
    "temp_s_10": 24.8,
    "wnd_max_0": 10.35,
    "wnd_prom_30": 9.67,
    "max_height": 32,
    "treatment": "H",
    "temp_l_0": 28.8,
    "date": "21/2/19",
    "wnd_min_200": 17.32
}, {
    "ms_v": 15.65,
    "temp_s_5": 29.7,
    "wnd_max_30": 15.97,
    "std_dev": 7.12,
    "wnd_prom_0": 8.25,
    "temp_s_0": 40.7,
    "status": "ok",
    "rep": "1",
    "wnd_max_200": 24.98,
    "median": 17.0,
    "sec_noise": 15.0,
    "volume": 2.9,
    "temp_l_10": 24.6,
    "orientation": "H",
    "wnd_min_0": 7.04,
    "ms_h": 44.0,
    "filename": "19_2_21_B2P1.txt",
    "temp_l_5": 29.0,
    "wnd_min_30": 7.42,
    "block": "2",
    "entropy": 7.55,
    "wnd_prom_200": 18.73,
    "density": 20.55,
    "temp_s_10": 24.7,
    "wnd_max_0": 9.45,
    "wnd_prom_30": 11.7,
    "max_height": 37,
    "treatment": "P",
    "temp_l_0": 36.8,
    "date": "21/2/19",
    "wnd_min_200": 12.48
}, {
    "ms_v": 9.27,
    "temp_s_5": 31.6,
    "wnd_max_30": 15.97,
    "std_dev": 8.03,
    "wnd_prom_0": 8.25,
    "temp_s_0": 41.0,
    "status": "ok",
    "rep": "2",
    "wnd_max_200": 24.98,
    "median": 17.0,
    "sec_noise": 13.0,
    "volume": 3.03,
    "temp_l_10": 24.1,
    "orientation": "H",
    "wnd_min_0": 7.04,
    "ms_h": 37.55,
    "filename": "19_2_21_B2P2.txt",
    "temp_l_5": 31.0,
    "wnd_min_30": 7.42,
    "block": "2",
    "entropy": 7.08,
    "wnd_prom_200": 18.73,
    "density": 15.44,
    "temp_s_10": 24.8,
    "wnd_max_0": 9.45,
    "wnd_prom_30": 11.7,
    "max_height": 56,
    "treatment": "P",
    "temp_l_0": 38.4,
    "date": "21/2/19",
    "wnd_min_200": 12.48
}, {
    "ms_v": 14.42,
    "temp_s_5": 30.3,
    "wnd_max_30": 15.97,
    "std_dev": 8.28,
    "wnd_prom_0": 8.25,
    "temp_s_0": 44.2,
    "status": "ok",
    "rep": "3",
    "wnd_max_200": 24.98,
    "median": 19.0,
    "sec_noise": 11.0,
    "volume": 3.44,
    "temp_l_10": 23.7,
    "orientation": "H",
    "wnd_min_0": 7.04,
    "ms_h": 28.73,
    "filename": "19_2_21_B2P3.txt",
    "temp_l_5": 28.8,
    "wnd_min_30": 7.42,
    "block": "2",
    "entropy": 7.48,
    "wnd_prom_200": 18.73,
    "density": 12.53,
    "temp_s_10": 24.3,
    "wnd_max_0": 9.45,
    "wnd_prom_30": 11.7,
    "max_height": 47,
    "treatment": "P",
    "temp_l_0": 39.6,
    "date": "21/2/19",
    "wnd_min_200": 12.48
}, {
    "ms_v": 22.03,
    "temp_s_5": 30.3,
    "wnd_max_30": 13.5,
    "std_dev": 26.16,
    "wnd_prom_0": 5.4,
    "temp_s_0": 31.1,
    "status": "ok",
    "rep": "1",
    "wnd_max_200": 26.09,
    "median": 24.0,
    "sec_noise": 5.0,
    "volume": 5.68,
    "temp_l_10": 25.8,
    "orientation": "H",
    "wnd_min_0": 4.62,
    "ms_h": 51.55,
    "filename": "19_2_21_B2V1.txt",
    "temp_l_5": 31.9,
    "wnd_min_30": 5.39,
    "block": "2",
    "entropy": 6.61,
    "wnd_prom_200": 19.65,
    "density": 12.96,
    "temp_s_10": 24.3,
    "wnd_max_0": 6.17,
    "wnd_prom_30": 9.45,
    "max_height": 186,
    "treatment": "V",
    "temp_l_0": 29.5,
    "date": "21/2/19",
    "wnd_min_200": 13.21
}, {
    "ms_v": 39.21,
    "temp_s_5": 30.8,
    "wnd_max_30": 13.5,
    "std_dev": 50.55,
    "wnd_prom_0": 5.4,
    "temp_s_0": 31.9,
    "status": "ok",
    "rep": "2",
    "wnd_max_200": 26.09,
    "median": 39.0,
    "sec_noise": 16.0,
    "volume": 9.99,
    "temp_l_10": 24.6,
    "orientation": "H",
    "wnd_min_0": 4.62,
    "ms_h": 51.24,
    "filename": "19_2_21_B2V2.txt",
    "temp_l_5": 28.2,
    "wnd_min_30": 5.39,
    "block": "2",
    "entropy": 6.5,
    "wnd_prom_200": 19.65,
    "density": 9.06,
    "temp_s_10": 24.6,
    "wnd_max_0": 6.17,
    "wnd_prom_30": 9.45,
    "max_height": 357,
    "treatment": "V",
    "temp_l_0": 30.8,
    "date": "21/2/19",
    "wnd_min_200": 13.21
}, {
    "ms_v": 31.93,
    "temp_s_5": 28.6,
    "wnd_max_30": 13.5,
    "std_dev": 37.13,
    "wnd_prom_0": 5.4,
    "temp_s_0": 31.8,
    "status": "ok",
    "rep": "3",
    "wnd_max_200": 26.09,
    "median": 33.0,
    "sec_noise": 11.0,
    "volume": 7.9,
    "temp_l_10": 23.7,
    "orientation": "H",
    "wnd_min_0": 4.62,
    "ms_h": 40.59,
    "filename": "19_2_21_B2V3.txt",
    "temp_l_5": 27.3,
    "wnd_min_30": 5.39,
    "block": "2",
    "entropy": 6.59,
    "wnd_prom_200": 19.65,
    "density": 9.18,
    "temp_s_10": 23.4,
    "wnd_max_0": 6.17,
    "wnd_prom_30": 9.45,
    "max_height": 243,
    "treatment": "V",
    "temp_l_0": 28.9,
    "date": "21/2/19",
    "wnd_min_200": 13.21
}, {
    "ms_v": 1.85,
    "temp_s_5": 26.35,
    "wnd_max_30": 15.2,
    "std_dev": 7.67,
    "wnd_prom_0": 8.55,
    "temp_s_0": 35.55,
    "status": "ok",
    "rep": "1",
    "wnd_max_200": 26.48,
    "median": 15.0,
    "sec_noise": 15.0,
    "volume": 2.84,
    "temp_l_10": 22.6,
    "orientation": "H",
    "wnd_min_0": 6.3,
    "ms_h": 68.48,
    "filename": "19_2_21_B3H1.txt",
    "temp_l_5": 26.15,
    "wnd_min_30": 7.18,
    "block": "3",
    "entropy": 6.83,
    "wnd_prom_200": 20.18,
    "density": 24.76,
    "temp_s_10": 22.5,
    "wnd_max_0": 10.8,
    "wnd_prom_30": 11.19,
    "max_height": 65,
    "treatment": "H",
    "temp_l_0": 34.65,
    "date": "21/2/19",
    "wnd_min_200": 13.89
}, {
    "ms_v": 0.72,
    "temp_s_5": 28.7,
    "wnd_max_30": 15.2,
    "std_dev": 5.0,
    "wnd_prom_0": 8.55,
    "temp_s_0": 36.45,
    "status": "ok",
    "rep": "2",
    "wnd_max_200": 26.48,
    "median": 12.0,
    "sec_noise": 15.0,
    "volume": 2.09,
    "temp_l_10": 23.2,
    "orientation": "H",
    "wnd_min_0": 6.3,
    "ms_h": 52.53,
    "filename": "19_2_21_B3H2.txt",
    "temp_l_5": 27.5,
    "wnd_min_30": 7.18,
    "block": "3",
    "entropy": 7.44,
    "wnd_prom_200": 20.18,
    "density": 25.49,
    "temp_s_10": 23.5,
    "wnd_max_0": 10.8,
    "wnd_prom_30": 11.19,
    "max_height": 28,
    "treatment": "H",
    "temp_l_0": 34.65,
    "date": "21/2/19",
    "wnd_min_200": 13.89
}, {
    "ms_v": 1.88,
    "temp_s_5": 28.1,
    "wnd_max_30": 15.2,
    "std_dev": 7.56,
    "wnd_prom_0": 8.55,
    "temp_s_0": 31.0,
    "status": "ok",
    "rep": "3",
    "wnd_max_200": 26.48,
    "median": 14.0,
    "sec_noise": 18.0,
    "volume": 2.56,
    "temp_l_10": 23.25,
    "orientation": "H",
    "wnd_min_0": 6.3,
    "ms_h": 105.16,
    "filename": "19_2_21_B3H3.txt",
    "temp_l_5": 28.35,
    "wnd_min_30": 7.18,
    "block": "3",
    "entropy": 5.8,
    "wnd_prom_200": 20.18,
    "density": 41.76,
    "temp_s_10": 23.95,
    "wnd_max_0": 10.8,
    "wnd_prom_30": 11.19,
    "max_height": 104,
    "treatment": "H",
    "temp_l_0": 30.5,
    "date": "21/2/19",
    "wnd_min_200": 13.89
}, {
    "ms_v": 10.18,
    "temp_s_5": 29.35,
    "wnd_max_30": 17.34,
    "std_dev": 7.88,
    "wnd_prom_0": 7.65,
    "temp_s_0": 39.7,
    "status": "ok",
    "rep": "1",
    "wnd_max_200": 25.52,
    "median": 12.0,
    "sec_noise": 10.0,
    "volume": 2.39,
    "temp_l_10": 23.45,
    "orientation": "H",
    "wnd_min_0": 6.41,
    "ms_h": 15.99,
    "filename": "19_2_21_B3P1.txt",
    "temp_l_5": 27.5,
    "wnd_min_30": 8.1,
    "block": "3",
    "entropy": 7.43,
    "wnd_prom_200": 19.56,
    "density": 10.94,
    "temp_s_10": 23.9,
    "wnd_max_0": 8.89,
    "wnd_prom_30": 12.72,
    "max_height": 41,
    "treatment": "P",
    "temp_l_0": 36.3,
    "date": "21/2/19",
    "wnd_min_200": 13.61
}, {
    "ms_v": 13.21,
    "temp_s_5": 29.7,
    "wnd_max_30": 17.34,
    "std_dev": 9.51,
    "wnd_prom_0": 7.65,
    "temp_s_0": 39.65,
    "status": "ok",
    "rep": "2",
    "wnd_max_200": 25.52,
    "median": 17.0,
    "sec_noise": 8.0,
    "volume": 3.15,
    "temp_l_10": 23.7,
    "orientation": "H",
    "wnd_min_0": 6.41,
    "ms_h": 35.31,
    "filename": "19_2_21_B3P2.txt",
    "temp_l_5": 29.6,
    "wnd_min_30": 8.1,
    "block": "3",
    "entropy": 7.22,
    "wnd_prom_200": 19.56,
    "density": 15.41,
    "temp_s_10": 24.0,
    "wnd_max_0": 8.89,
    "wnd_prom_30": 12.72,
    "max_height": 61,
    "treatment": "P",
    "temp_l_0": 37.5,
    "date": "21/2/19",
    "wnd_min_200": 13.61
}, {
    "ms_v": 13.03,
    "temp_s_5": 29.55,
    "wnd_max_30": 17.34,
    "std_dev": 6.33,
    "wnd_prom_0": 7.65,
    "temp_s_0": 43.9,
    "status": "ok",
    "rep": "3",
    "wnd_max_200": 25.52,
    "median": 12.0,
    "sec_noise": 7.0,
    "volume": 2.32,
    "temp_l_10": 23.35,
    "orientation": "H",
    "wnd_min_0": 6.41,
    "ms_h": 40.9,
    "filename": "19_2_21_B3P3.txt",
    "temp_l_5": 27.5,
    "wnd_min_30": 8.1,
    "block": "3",
    "entropy": 7.46,
    "wnd_prom_200": 19.56,
    "density": 23.28,
    "temp_s_10": 23.9,
    "wnd_max_0": 8.89,
    "wnd_prom_30": 12.72,
    "max_height": 35,
    "treatment": "P",
    "temp_l_0": 37.35,
    "date": "21/2/19",
    "wnd_min_200": 13.61
}, {
    "ms_v": 41.26,
    "temp_s_5": 29.0,
    "wnd_max_30": 11.59,
    "std_dev": 47.18,
    "wnd_prom_0": 5.37,
    "temp_s_0": 34.0,
    "status": "ok",
    "rep": "1",
    "wnd_max_200": 26.9,
    "median": 42.0,
    "sec_noise": 14.0,
    "volume": 9.91,
    "temp_l_10": 24.45,
    "orientation": "H",
    "wnd_min_0": 4.5,
    "ms_h": 62.38,
    "filename": "19_2_21_B3V1.txt",
    "temp_l_5": 30.05,
    "wnd_min_30": 6.3,
    "block": "3",
    "entropy": 7.26,
    "wnd_prom_200": 19.9,
    "density": 10.45,
    "temp_s_10": 23.75,
    "wnd_max_0": 6.24,
    "wnd_prom_30": 8.94,
    "max_height": 233,
    "treatment": "V",
    "temp_l_0": 32.2,
    "date": "21/2/19",
    "wnd_min_200": 12.9
}, {
    "ms_v": 65.82,
    "temp_s_5": 29.55,
    "wnd_max_30": 11.59,
    "std_dev": 56.03,
    "wnd_prom_0": 5.37,
    "temp_s_0": 34.0,
    "status": "ok",
    "rep": "2",
    "wnd_max_200": 26.9,
    "median": 87.0,
    "sec_noise": 6.0,
    "volume": 15.86,
    "temp_l_10": 23.95,
    "orientation": "H",
    "wnd_min_0": 4.5,
    "ms_h": 39.86,
    "filename": "19_2_21_B3V2.txt",
    "temp_l_5": 27.7,
    "wnd_min_30": 6.3,
    "block": "3",
    "entropy": 7.68,
    "wnd_prom_200": 19.9,
    "density": 6.66,
    "temp_s_10": 23.95,
    "wnd_max_0": 6.24,
    "wnd_prom_30": 8.94,
    "max_height": 246,
    "treatment": "V",
    "temp_l_0": 33.9,
    "date": "21/2/19",
    "wnd_min_200": 12.9
}, {
    "ms_v": 41.67,
    "temp_s_5": 29.1,
    "wnd_max_30": 11.59,
    "std_dev": 41.41,
    "wnd_prom_0": 5.37,
    "temp_s_0": 37.6,
    "status": "ok",
    "rep": "3",
    "wnd_max_200": 26.9,
    "median": 48.0,
    "sec_noise": 7.0,
    "volume": 10.48,
    "temp_l_10": 23.6,
    "orientation": "H",
    "wnd_min_0": 4.5,
    "ms_h": 17.29,
    "filename": "19_2_21_B3V3.txt",
    "temp_l_5": 28.1,
    "wnd_min_30": 6.3,
    "block": "3",
    "entropy": 7.54,
    "wnd_prom_200": 19.9,
    "density": 5.62,
    "temp_s_10": 23.3,
    "wnd_max_0": 6.24,
    "wnd_prom_30": 8.94,
    "max_height": 194,
    "treatment": "V",
    "temp_l_0": 35.15,
    "date": "21/2/19",
    "wnd_min_200": 12.9
}, {
    "ms_h": 50.29,
    "status": "ok",
    "filename": "20_5_26_B1H1.txt",
    "sec_noise": 16.0,
    "std_dev": 3.51,
    "ms_v": 0,
    "treatment": "H",
    "rep": "1",
    "median": 9.0,
    "block": "1",
    "entropy": 7.62,
    "density": 32.03,
    "max_height": 17,
    "volume": 1.57,
    "orientation": "V",
    "date": "26/5/20"
}, {
    "ms_h": 80.62,
    "status": "ok",
    "filename": "20_5_26_B1H2.txt",
    "sec_noise": 31.0,
    "std_dev": 6.34,
    "ms_v": 0,
    "treatment": "H",
    "rep": "2",
    "median": 21.0,
    "block": "1",
    "entropy": 7.47,
    "density": 22.59,
    "max_height": 33,
    "volume": 3.57,
    "orientation": "V",
    "date": "26/5/20"
}, {
    "ms_h": 49.48,
    "status": "ok",
    "filename": "20_5_26_B1H3.txt",
    "sec_noise": 18.0,
    "std_dev": 5.18,
    "ms_v": 0,
    "treatment": "H",
    "rep": "3",
    "median": 10.0,
    "block": "1",
    "entropy": 7.49,
    "density": 25.31,
    "max_height": 27,
    "volume": 1.96,
    "orientation": "V",
    "date": "26/5/20"
}, {
    "ms_h": 24.9,
    "status": "ok",
    "filename": "20_5_26_B1P1.txt",
    "sec_noise": 15.0,
    "std_dev": 6.56,
    "ms_v": 4.81,
    "treatment": "P",
    "rep": "1",
    "median": 19,
    "block": "1",
    "entropy": 7.0,
    "density": 9.41,
    "max_height": 43,
    "volume": 3.16,
    "orientation": "V",
    "date": "26/5/20"
}, {
    "ms_h": 24.29,
    "status": "ok",
    "filename": "20_5_26_B1P2.txt",
    "sec_noise": 13.0,
    "std_dev": 8.12,
    "ms_v": 5.66,
    "treatment": "P",
    "rep": "2",
    "median": 14,
    "block": "1",
    "entropy": 5.49,
    "density": 11.86,
    "max_height": 145,
    "volume": 2.53,
    "orientation": "V",
    "date": "26/5/20"
}, {
    "ms_h": 33.99,
    "status": "ok",
    "filename": "20_5_26_B1P3.txt",
    "sec_noise": 8.0,
    "std_dev": 6.73,
    "ms_v": 6.43,
    "treatment": "P",
    "rep": "3",
    "median": 13.0,
    "block": "1",
    "entropy": 7.03,
    "density": 17.6,
    "max_height": 49,
    "volume": 2.3,
    "orientation": "V",
    "date": "26/5/20"
}, {
    "ms_h": 88.5,
    "status": "ok",
    "filename": "20_5_26_B1V1.txt",
    "sec_noise": 11.0,
    "std_dev": 31.0,
    "ms_v": 32.72,
    "treatment": "V",
    "rep": "1",
    "median": 42.0,
    "block": "1",
    "entropy": 7.41,
    "density": 13.96,
    "max_height": 154,
    "volume": 8.68,
    "orientation": "V",
    "date": "26/5/20"
}, {
    "ms_h": 51.51,
    "status": "ok",
    "filename": "20_5_26_B1V2.txt",
    "sec_noise": 11.0,
    "std_dev": 29.63,
    "ms_v": 23.48,
    "treatment": "V",
    "rep": "2",
    "median": 33,
    "block": "1",
    "entropy": 6.77,
    "density": 10.37,
    "max_height": 191,
    "volume": 7.23,
    "orientation": "V",
    "date": "26/5/20"
}, {
    "ms_h": 68.31,
    "status": "ok",
    "filename": "20_5_26_B1V3.txt",
    "sec_noise": 8.0,
    "std_dev": 34.21,
    "ms_v": 28.48,
    "treatment": "V",
    "rep": "3",
    "median": 29.0,
    "block": "1",
    "entropy": 6.73,
    "density": 13.6,
    "max_height": 223,
    "volume": 7.12,
    "orientation": "V",
    "date": "26/5/20"
}, {
    "ms_h": 27.46,
    "status": "ok",
    "filename": "20_5_26_B2H1.txt",
    "sec_noise": 17.0,
    "std_dev": 3.43,
    "ms_v": 0,
    "treatment": "H",
    "rep": "1",
    "median": 13.0,
    "block": "2",
    "entropy": 7.27,
    "density": 12.14,
    "max_height": 22,
    "volume": 2.26,
    "orientation": "V",
    "date": "26/5/20"
}, {
    "ms_h": 35.21,
    "status": "ok",
    "filename": "20_5_26_B2H2.txt",
    "sec_noise": 16.0,
    "std_dev": 4.72,
    "ms_v": 0,
    "treatment": "H",
    "rep": "2",
    "median": 14.0,
    "block": "2",
    "entropy": 7.58,
    "density": 14.22,
    "max_height": 25,
    "volume": 2.48,
    "orientation": "V",
    "date": "26/5/20"
}, {
    "ms_h": 48.23,
    "status": "ok",
    "filename": "20_5_26_B2H3.txt",
    "sec_noise": 17.0,
    "std_dev": 3.85,
    "ms_v": 0,
    "treatment": "H",
    "rep": "3",
    "median": 8.0,
    "block": "2",
    "entropy": 7.49,
    "density": 33.67,
    "max_height": 21,
    "volume": 1.43,
    "orientation": "V",
    "date": "26/5/20"
}, {
    "ms_h": 40.84,
    "status": "ok",
    "filename": "20_5_26_B2P1.txt",
    "sec_noise": 11.0,
    "std_dev": 7.66,
    "ms_v": 8.59,
    "treatment": "P",
    "rep": "1",
    "median": 16.0,
    "block": "2",
    "entropy": 7.35,
    "density": 16.82,
    "max_height": 46,
    "volume": 2.94,
    "orientation": "V",
    "date": "26/5/20"
}, {
    "ms_h": 15.12,
    "status": "ok",
    "filename": "20_5_26_B2P2.txt",
    "sec_noise": 11.0,
    "std_dev": 6.94,
    "ms_v": 6.69,
    "treatment": "P",
    "rep": "2",
    "median": 16.0,
    "block": "2",
    "entropy": 7.64,
    "density": 7.71,
    "max_height": 35,
    "volume": 2.83,
    "orientation": "V",
    "date": "26/5/20"
}, {
    "ms_h": 23.7,
    "status": "ok",
    "filename": "20_5_26_B2P3.txt",
    "sec_noise": 10.0,
    "std_dev": 5.78,
    "ms_v": 8.55,
    "treatment": "P",
    "rep": "3",
    "median": 12.0,
    "block": "2",
    "entropy": 7.4,
    "density": 15.06,
    "max_height": 33,
    "volume": 2.14,
    "orientation": "V",
    "date": "26/5/20"
}, {
    "ms_h": 34.74,
    "status": "ok",
    "filename": "20_5_26_B2V1.txt",
    "sec_noise": 10.0,
    "std_dev": 23.08,
    "ms_v": 20.18,
    "treatment": "V",
    "rep": "1",
    "median": 24,
    "block": "2",
    "entropy": 6.45,
    "density": 10.23,
    "max_height": 194,
    "volume": 5.37,
    "orientation": "V",
    "date": "26/5/20"
}, {
    "ms_h": 29.95,
    "status": "ok",
    "filename": "20_5_26_B2V2.txt",
    "sec_noise": 8.0,
    "std_dev": 11.03,
    "ms_v": 14.28,
    "treatment": "V",
    "rep": "2",
    "median": 22.0,
    "block": "2",
    "entropy": 7.55,
    "density": 10.88,
    "max_height": 58,
    "volume": 4.06,
    "orientation": "V",
    "date": "26/5/20"
}, {
    "ms_h": 24.6,
    "status": "ok",
    "filename": "20_5_26_B2V3.txt",
    "sec_noise": 6.0,
    "std_dev": 34.85,
    "ms_v": 34.58,
    "treatment": "V",
    "rep": "3",
    "median": 38.0,
    "block": "2",
    "entropy": 7.01,
    "density": 6.85,
    "max_height": 205,
    "volume": 8.63,
    "orientation": "V",
    "date": "26/5/20"
}, {
    "ms_h": 50.88,
    "status": "ok",
    "filename": "20_5_26_B3H1.txt",
    "sec_noise": 25.0,
    "std_dev": 4.4,
    "ms_v": 0,
    "treatment": "H",
    "rep": "1",
    "median": 14.0,
    "block": "3",
    "entropy": 7.36,
    "density": 21.21,
    "max_height": 27,
    "volume": 2.4,
    "orientation": "V",
    "date": "26/5/20"
}, {
    "ms_h": 90.41,
    "status": "ok",
    "filename": "20_5_26_B3H2.txt",
    "sec_noise": 19.0,
    "std_dev": 4.09,
    "ms_v": 0,
    "treatment": "H",
    "rep": "2",
    "median": 12.0,
    "block": "3",
    "entropy": 7.5,
    "density": 43.75,
    "max_height": 22,
    "volume": 2.07,
    "orientation": "V",
    "date": "26/5/20"
}, {
    "ms_h": 69.11,
    "status": "ok",
    "filename": "20_5_26_B3H3.txt",
    "sec_noise": 20.0,
    "std_dev": 4.8,
    "ms_v": 0,
    "treatment": "H",
    "rep": "3",
    "median": 14.0,
    "block": "3",
    "entropy": 7.3,
    "density": 29.64,
    "max_height": 30,
    "volume": 2.33,
    "orientation": "V",
    "date": "26/5/20"
}, {
    "ms_h": 20.56,
    "status": "ok",
    "filename": "20_5_26_B3P1.txt",
    "sec_noise": 10.0,
    "std_dev": 6.8,
    "ms_v": 10.06,
    "treatment": "P",
    "rep": "1",
    "median": 15.0,
    "block": "3",
    "entropy": 7.63,
    "density": 11.4,
    "max_height": 34,
    "volume": 2.69,
    "orientation": "V",
    "date": "26/5/20"
}, {
    "ms_h": 27.57,
    "status": "ok",
    "filename": "20_5_26_B3P2.txt",
    "sec_noise": 6.0,
    "std_dev": 12.59,
    "ms_v": 11.76,
    "treatment": "P",
    "rep": "2",
    "median": 16.0,
    "block": "3",
    "entropy": 6.87,
    "density": 11.46,
    "max_height": 86,
    "volume": 3.43,
    "orientation": "V",
    "date": "26/5/20"
}, {
    "ms_h": 12.16,
    "status": "ok",
    "filename": "20_5_26_B3P3.txt",
    "sec_noise": 16.0,
    "std_dev": 5.3,
    "ms_v": 5.75,
    "treatment": "P",
    "rep": "3",
    "median": 12.0,
    "block": "3",
    "entropy": 7.36,
    "density": 8.87,
    "max_height": 30,
    "volume": 2.02,
    "orientation": "V",
    "date": "26/5/20"
}, {
    "ms_h": 39.18,
    "status": "ok",
    "filename": "20_5_26_B3V1.txt",
    "sec_noise": 9.0,
    "std_dev": 35.98,
    "ms_v": 31.55,
    "treatment": "V",
    "rep": "1",
    "median": 34.0,
    "block": "3",
    "entropy": 7.11,
    "density": 8.9,
    "max_height": 203,
    "volume": 7.95,
    "orientation": "V",
    "date": "26/5/20"
}, {
    "ms_h": 33.16,
    "status": "ok",
    "filename": "20_5_26_B3V2.txt",
    "sec_noise": 5.0,
    "std_dev": 42.56,
    "ms_v": 36.81,
    "treatment": "V",
    "rep": "2",
    "median": 40.0,
    "block": "3",
    "entropy": 7.3,
    "density": 7.59,
    "max_height": 201,
    "volume": 9.22,
    "orientation": "V",
    "date": "26/5/20"
}, {
    "ms_h": 56.38,
    "status": "ok",
    "filename": "20_5_26_B3V3.txt",
    "sec_noise": 5.0,
    "std_dev": 39.02,
    "ms_v": 33.1,
    "treatment": "V",
    "rep": "3",
    "median": 33.0,
    "block": "3",
    "entropy": 6.54,
    "density": 10.4,
    "max_height": 302,
    "volume": 8.6,
    "orientation": "V",
    "date": "26/5/20"
}]